dm_cache_data.sv
import cache_def::*;

// Memória de dados da cache: 1024 linhas de 128 bits (porta única)
module dm_cache_data(
  input  bit            clk,
  input  cache_req_type data_req,   // índice + write enable
  input  cache_data_type data_write, // linha a ser escrita
  output cache_data_type data_read   // linha lida (combinacional)
);
  timeunit 1ns; timeprecision 1ps;

  cache_data_type data_mem[0:1023];

  // Inicializa tudo com zero (cache começa vazia/inválida)
  initial begin
    for (int i = 0; i < 1024; i++)
      data_mem[i] = '0;
  end

  // Leitura combinacional: resultado disponível imediatamente
  assign data_read = data_mem[data_req.index];

  // Escrita síncrona: só ocorre na borda de subida se we == 1
  always_ff @(posedge clk) begin
    if (data_req.we)
      data_mem[data_req.index] <= data_write;
  end

endmodule

dm_cache_tag.sv
import cache_def::*;

// Memória de tags da cache: 1024 entradas (valid + dirty + tag)
module dm_cache_tag(
  input  bit            clk,
  input  cache_req_type tag_req,   // índice + write enable
  input  cache_tag_type tag_write, // entrada a ser escrita
  output cache_tag_type tag_read   // entrada lida (combinacional)
);
  timeunit 1ns; timeprecision 1ps;

  cache_tag_type tag_mem[0:1023];

  initial begin
    for (int i = 0; i < 1024; i++)
      tag_mem[i] = '0;  // valid e dirty começam em 0
  end

  // Leitura combinacional
  assign tag_read = tag_mem[tag_req.index];

  // Escrita síncrona
  always_ff @(posedge clk) begin
    if (tag_req.we)
      tag_mem[tag_req.index] <= tag_write;
  end

endmodule

dm_cache_fsm.sv
import cache_def::*;

// Controlador de cache: FSM com 4 estados
//   idle        -> aguarda requisição do processador
//   compare_tag -> verifica hit/miss e atualiza tag memory
//   allocate    -> espera bloco chegar da memória principal (read miss)
//   write_back  -> escreve linha dirty na memória antes de alocar nova
module dm_cache_fsm(
  input  bit            clk,
  input  bit            rst,
  input  cpu_req_type   cpu_req,  // requisição do processador
  input  mem_data_type  mem_data, // resposta da memória principal
  output mem_req_type   mem_req,  // requisição para a memória principal
  output cpu_result_type cpu_res  // resultado para o processador
);
  timeunit 1ns; timeprecision 1ps;

  typedef enum {idle, compare_tag, allocate, write_back} cache_state_type;

  cache_state_type vstate, rstate; // próximo estado / estado atual

  // Sinais de interface com a tag memory
  cache_tag_type  tag_read;
  cache_tag_type  tag_write;
  cache_req_type  tag_req;

  // Sinais de interface com a data memory
  cache_data_type data_read;
  cache_data_type data_write;
  cache_req_type  data_req;

  // Variáveis combinacionais (saídas calculadas antes de registrar)
  cpu_result_type v_cpu_res;
  mem_req_type    v_mem_req;

  assign mem_req = v_mem_req;
  assign cpu_res = v_cpu_res;

  always_comb begin
    // --- valores padrão (evitam latches) ---
    vstate            = rstate;
    v_cpu_res.data    = '0;
    v_cpu_res.ready   = '0;
    tag_write.valid   = '0;
    tag_write.dirty   = '0;
    tag_write.tag     = '0;

    tag_req.we    = '0;
    tag_req.index = cpu_req.addr[13:4];  // bits de índice (direct-mapped)

    data_req.we    = '0;
    data_req.index = cpu_req.addr[13:4];

    // Prepara data_write com a linha atual, sobrescrevendo a palavra endereçada
    data_write = data_read;
    case (cpu_req.addr[3:2])  // offset de palavra dentro do bloco
      2'b00: data_write[31:0]   = cpu_req.data;
      2'b01: data_write[63:32]  = cpu_req.data;
      2'b10: data_write[95:64]  = cpu_req.data;
      2'b11: data_write[127:96] = cpu_req.data;
    endcase

    // Seleciona a palavra de 32 bits correta para enviar à CPU
    case (cpu_req.addr[3:2])
      2'b00: v_cpu_res.data = data_read[31:0];
      2'b01: v_cpu_res.data = data_read[63:32];
      2'b10: v_cpu_res.data = data_read[95:64];
      2'b11: v_cpu_res.data = data_read[127:96];
    endcase

    v_mem_req.addr  = cpu_req.addr;
    v_mem_req.data  = data_read;  // dado para write-back (se necessário)
    v_mem_req.rw    = '0;
    v_mem_req.valid = '0;

    // --- FSM ---
    case (rstate)

      idle: begin
        if (cpu_req.valid)
          vstate = compare_tag;
      end

      compare_tag: begin
        if (cpu_req.addr[TAGMSB:TAGLSB] == tag_read.tag && tag_read.valid) begin
          // HIT: dado está na cache
          v_cpu_res.ready = '1;

          if (cpu_req.rw) begin
            // Write hit: atualiza dado e marca linha como dirty
            tag_req.we  = '1;
            data_req.we = '1;
            tag_write.tag   = tag_read.tag;
            tag_write.valid = '1;
            tag_write.dirty = '1;
          end

          vstate = idle;
        end
        else begin
          // MISS: atualiza tag com novo endereço
          tag_req.we      = '1;
          tag_write.valid = '1;
          tag_write.tag   = cpu_req.addr[TAGMSB:TAGLSB];
          tag_write.dirty = cpu_req.rw; // sujo apenas se for write miss

          v_mem_req.valid = '1;

          if (tag_read.valid == 1'b0 || tag_read.dirty == 1'b0) begin
            // Miss com linha limpa ou inválida: apenas busca da memória
            vstate = allocate;
          end
          else begin
            // Miss com linha dirty: precisa fazer write-back antes
            v_mem_req.addr = {tag_read.tag, cpu_req.addr[TAGLSB-1:0]};
            v_mem_req.rw   = '1;
            vstate = write_back;
          end
        end
      end

      allocate: begin
        // Aguarda a memória principal responder com o novo bloco
        if (mem_data.ready) begin
          data_write  = mem_data.data;
          data_req.we = '1;
          vstate = compare_tag; // re-executa compare para tratar write miss
        end
      end

      write_back: begin
        // Aguarda confirmação de escrita na memória, depois busca novo bloco
        if (mem_data.ready) begin
          v_mem_req.valid = '1;
          v_mem_req.rw    = '0;
          vstate = allocate;
        end
      end

    endcase
  end

  // Registro de estado: atualiza na borda de subida ou reseta para idle
  always_ff @(posedge clk) begin
    if (rst)
      rstate <= idle;
    else
      rstate <= vstate;
  end

  // Instancia as memórias internas (conexão por nome implícita via .*)
  dm_cache_tag  ctag(.*);
  dm_cache_data cdata(.*);

endmodule

MAIN.testing.sv
import cache_def::*;

module tb_dm_cache;
    // Testbench signals
    bit clk;
    bit rst;
    cpu_req_type cpu_req;
    mem_data_type mem_data;
    
    mem_req_type mem_req;
    cpu_result_type cpu_res;

    // Instantiate the Cache FSM (Design Under Test)
    dm_cache_fsm dut (
        .clk(clk),
        .rst(rst),
        .cpu_req(cpu_req),
        .mem_data(mem_data),
        .mem_req(mem_req),
        .cpu_res(cpu_res)
    );

    // Clock generator (50MHz / 20ns period)
    always #10 clk = ~clk;

    // Simulate Main Memory Behavior
    always @(posedge clk) begin
        if (mem_req.valid) begin
            // Simulate a 3-cycle memory latency delay
            repeat (3) @(posedge clk);
            mem_data.ready <= 1'b1;
            if (mem_req.rw == 1'b0) begin
                // On a memory read request, return a dummy pattern
                mem_data.data <= {32'hDEADBEEF, 32'hCAFEBABE, 32'hAAAA5555, 32'h12345678};
            end
        end else begin
            mem_data.ready <= 1'b0;
        end
    end

    // Stimulus block
    initial begin
        // Setup waveform dumping for GTKWave
        $dumpfile("dump.vcd");
        $dumpvars(0, tb_dm_cache);

        // Initialize signals & Reset system
        clk = 0;
        rst = 1;
        cpu_req = '{0, 0, 0, 0};
        mem_data = '{0, 0};
        #40;
        rst = 0;
        #20;

        // --- TEST 1: Read Compulsory Miss ---
        $display("[TIME: %0t] Test 1: Reading Addr 32'h0000_1000 (Expect: MISS -> Allocate)", $time);
        cpu_req.addr  = 32'h0000_1000; 
        cpu_req.rw    = 1'b0; // Read
        cpu_req.valid = 1'b1;
        
        // Wait until cache declares data is ready
        while (!cpu_res.ready) @(posedge clk);
        $display("[TIME: %0t] Test 1 Success! Data Read: %h", $time, cpu_res.data);
        cpu_req.valid = 1'b0;
        #40;

        // --- TEST 2: Read Hit ---
        $display("[TIME: %0t] Test 2: Reading Addr 32'h0000_1000 again (Expect: HIT)", $time);
        cpu_req.addr  = 32'h0000_1000;
        cpu_req.rw    = 1'b0;
        cpu_req.valid = 1'b1;
        
        @(posedge clk);
        if (cpu_res.ready) 
            $display("[TIME: %0t] Test 2 Success! Cache Hit instantly. Data: %h", $time, cpu_res.data);
        cpu_req.valid = 1'b0;
        #40;

        // --- TEST 3: Write Hit (Dirtying the Line) ---
        $display("[TIME: %0t] Test 3: Writing to Addr 32'h0000_1000 (Expect: HIT -> Line marked Dirty)", $time);
        cpu_req.addr  = 32'h0000_1000;
        cpu_req.data  = 32'h5555_5555;
        cpu_req.rw    = 1'b1; // Write
        cpu_req.valid = 1'b1;
        
        while (!cpu_res.ready) @(posedge clk);
        cpu_req.valid = 1'b0;
        #40;

        // --- TEST 4: Conflict Miss with a Dirty Line (Write Back) ---
        $display("[TIME: %0t] Test 4: Reading Addr 32'h0004_1000 (Same index, diff tag. Expect: Conflict MISS -> Write_Back -> Allocate)", $time);
        cpu_req.addr  = 32'h0004_1000; // Maps to the same cache index
        cpu_req.rw    = 1'b0;
        cpu_req.valid = 1'b1;

        while (!cpu_res.ready) @(posedge clk);
        $display("[TIME: %0t] Test 4 Success! Data Read from new block: %h", $time, cpu_res.data);
        cpu_req.valid = 1'b0;
        
        #100;
        $finish;
    end

endmodule

dump.vcd
$date
	Thu May 28 15:31:04 2026
$end
$version
	Icarus Verilog
$end
$timescale
	1ps
$end
$scope module tb_dm_cache $end
$var wire 162 ! mem_req [161:0] $end
$var wire 33 " cpu_res [32:0] $end
$var reg 1 # clk $end
$var reg 66 $ cpu_req [65:0] $end
$var reg 129 % mem_data [128:0] $end
$var reg 1 & rst $end
$scope module dut $end
$var wire 1 # clk $end
$var wire 66 ' cpu_req [65:0] $end
$var wire 33 ( cpu_res [32:0] $end
$var wire 129 ) mem_data [128:0] $end
$var wire 162 * mem_req [161:0] $end
$var wire 1 & rst $end
$var wire 20 + tag_read [19:0] $end
$var wire 128 , data_read [127:0] $end
$var reg 11 - data_req [10:0] $end
$var reg 128 . data_write [127:0] $end
$var integer 32 / rstate [31:0] $end
$var reg 11 0 tag_req [10:0] $end
$var reg 20 1 tag_write [19:0] $end
$var reg 33 2 v_cpu_res [32:0] $end
$var reg 162 3 v_mem_req [161:0] $end
$var integer 32 4 vstate [31:0] $end
$scope module cdata $end
$var wire 1 # clk $end
$var wire 128 5 data_read [127:0] $end
$var wire 11 6 data_req [10:0] $end
$var wire 128 7 data_write [127:0] $end
$scope begin $ivl_for_loop1 $end
$var integer 32 8 i [31:0] $end
$upscope $end
$upscope $end
$scope module ctag $end
$var wire 1 # clk $end
$var wire 20 9 tag_read [19:0] $end
$var wire 11 : tag_req [10:0] $end
$var wire 20 ; tag_write [19:0] $end
$scope begin $ivl_for_loop0 $end
$var integer 32 < i [31:0] $end
$upscope $end
$upscope $end
$upscope $end
$upscope $end
$enddefinitions $end
$comment Show the parameter values. $end
$dumpall
$end
#0
$dumpvars
b10000000000 <
b0 ;
b0 :
b0 9
b10000000000 8
b0 7
b0 6
b0 5
b0 4
b0 3
b0 2
b0 1
b0 0
b0 /
b0 .
b0 -
b0 ,
b0 +
b0 *
b0 )
b0 (
b0 '
1&
b0 %
b0 $
0#
b0 "
b0 !
$end
#10000000000000
1#
#20000000000000
0#
#30000000000000
1#
#40000000000000
0#
0&
#50000000000000
1#
#60000000000000
b1 4
b10000000000000000000000000000000000000000000000000000000000000000000000000000000000000000000000000000000000000000000000000000000000000000000000 !
b10000000000000000000000000000000000000000000000000000000000000000000000000000000000000000000000000000000000000000000000000000000000000000000000 *
b10000000000000000000000000000000000000000000000000000000000000000000000000000000000000000000000000000000000000000000000000000000000000000000000 3
b1000000000 -
b1000000000 6
b1000000000 0
b1000000000 :
0#
b10000000000000000000000000000000000000000000001 $
b10000000000000000000000000000000000000000000001 '
#70000000000000
b10 4
b10000000000000000000000000000000000000000000000000000000000000000000000000000000000000000000000000000000000000000000000000000000000000000000001 !
b10000000000000000000000000000000000000000000000000000000000000000000000000000000000000000000000000000000000000000000000000000000000000000000001 *
b10000000000000000000000000000000000000000000000000000000000000000000000000000000000000000000000000000000000000000000000000000000000000000000001 3
b10000000000000000000 1
b10000000000000000000 ;
b1000000001 0
b1000000001 :
b1 /
1#
#80000000000000
0#
#90000000000000
b1000000000 0
b1000000000 :
b0 1
b0 ;
b10000000000000000000 +
b10000000000000000000 9
b10 /
1#
#100000000000000
0#
#110000000000000
1#
#120000000000000
0#
#130000000000000
1#
#140000000000000
0#
#150000000000000
b1000000001 -
b1000000001 6
b11011110101011011011111011101111110010101111111010111010101111101010101010101010010101010101010100010010001101000101011001111000 .
b11011110101011011011111011101111110010101111111010111010101111101010101010101010010101010101010100010010001101000101011001111000 7
b1 4
b110111101010110110111110111011111100101011111110101110101011111010101010101010100101010101010101000100100011010001010110011110001 %
b110111101010110110111110111011111100101011111110101110101011111010101010101010100101010101010101000100100011010001010110011110001 )
1#
#160000000000000
0#
#170000000000000
b0 4
b10000000000001101111010101101101111101110111111001010111111101011101010111110101010101010101001010101010101010001001000110100010101100111100001 !
b10000000000001101111010101101101111101110111111001010111111101011101010111110101010101010101001010101010101010001001000110100010101100111100001 *
b10000000000001101111010101101101111101110111111001010111111101011101010111110101010101010101001010101010101010001001000110100010101100111100001 3
b100100011010001010110011110001 "
b100100011010001010110011110001 (
b100100011010001010110011110001 2
b11011110101011011011111011101111110010101111111010111010101111101010101010101010010101010101010100000000000000000000000000000000 .
b11011110101011011011111011101111110010101111111010111010101111101010101010101010010101010101010100000000000000000000000000000000 7
b1000000000 -
b1000000000 6
b11011110101011011011111011101111110010101111111010111010101111101010101010101010010101010101010100010010001101000101011001111000 ,
b11011110101011011011111011101111110010101111111010111010101111101010101010101010010101010101010100010010001101000101011001111000 5
b1 /
1#
#180000000000000
0#
#190000000000000
b0 /
b11011110101011011011111011101111110010101111111010111010101111101010101010101010010101010101010100000000000000000000000000000000 .
b11011110101011011011111011101111110010101111111010111010101111101010101010101010010101010101010100000000000000000000000000000000 7
b100100011010001010110011110000 "
b100100011010001010110011110000 (
b100100011010001010110011110000 2
b0 4
b10000000000000000000000000000000000000000000000 $
b10000000000000000000000000000000000000000000000 '
1#
#200000000000000
0#
#210000000000000
1#
#220000000000000
0#
#230000000000000
b1 /
b0 4
b11011110101011011011111011101111110010101111111010111010101111101010101010101010010101010101010100000000000000000000000000000000 .
b11011110101011011011111011101111110010101111111010111010101111101010101010101010010101010101010100000000000000000000000000000000 7
b100100011010001010110011110001 "
b100100011010001010110011110001 (
b100100011010001010110011110001 2
1#
b10000000000000000000000000000000000000000000000 $
b10000000000000000000000000000000000000000000000 '
#240000000000000
0#
#250000000000000
b11011110101011011011111011101111110010101111111010111010101111101010101010101010010101010101010100000000000000000000000000000000 .
b11011110101011011011111011101111110010101111111010111010101111101010101010101010010101010101010100000000000000000000000000000000 7
b100100011010001010110011110000 "
b100100011010001010110011110000 (
b100100011010001010110011110000 2
b0 /
1#
#260000000000000
0#
#270000000000000
b11000000000000000000 1
b11000000000000000000 ;
b1000000001 -
b1000000001 6
b1000000001 0
b1000000001 :
b1 /
b0 4
b11011110101011011011111011101111110010101111111010111010101111101010101010101010010101010101010101010101010101010101010101010101 .
b11011110101011011011111011101111110010101111111010111010101111101010101010101010010101010101010101010101010101010101010101010101 7
b100100011010001010110011110001 "
b100100011010001010110011110001 (
b100100011010001010110011110001 2
1#
b10000000000000101010101010101010101010101010111 $
b10000000000000101010101010101010101010101010111 '
#280000000000000
0#
#290000000000000
b10000000000001101111010101101101111101110111111001010111111101011101010111110101010101010101001010101010101010101010101010101010101010101010101 !
b10000000000001101111010101101101111101110111111001010111111101011101010111110101010101010101001010101010101010101010101010101010101010101010101 *
b10000000000001101111010101101101111101110111111001010111111101011101010111110101010101010101001010101010101010101010101010101010101010101010101 3
b11000000000000000000 +
b11000000000000000000 9
b11011110101011011011111011101111110010101111111010111010101111101010101010101010010101010101010101010101010101010101010101010101 ,
b11011110101011011011111011101111110010101111111010111010101111101010101010101010010101010101010101010101010101010101010101010101 5
b0 /
b11011110101011011011111011101111110010101111111010111010101111101010101010101010010101010101010101010101010101010101010101010101 .
b11011110101011011011111011101111110010101111111010111010101111101010101010101010010101010101010101010101010101010101010101010101 7
b1000000000 -
b1000000000 6
b1000000000 0
b1000000000 :
b0 1
b0 ;
b10101010101010101010101010101010 "
b10101010101010101010101010101010 (
b10101010101010101010101010101010 2
b0 4
b10000000000000101010101010101010101010101010110 $
b10000000000000101010101010101010101010101010110 '
1#
#300000000000000
0#
#310000000000000
1#
#320000000000000
0#
#330000000000000
b10000000000000010000 1
b10000000000000010000 ;
b1000000001 0
b1000000001 :
b1 /
b11 4
b10000000000001101111010101101101111101110111111001010111111101011101010111110101010101010101001010101010101010101010101010101010101010101010111 !
b10000000000001101111010101101101111101110111111001010111111101011101010111110101010101010101001010101010101010101010101010101010101010101010111 *
b10000000000001101111010101101101111101110111111001010111111101011101010111110101010101010101001010101010101010101010101010101010101010101010111 3
b10101010101010101010101010101010 "
b10101010101010101010101010101010 (
b10101010101010101010101010101010 2
1#
b10000010000000000000101010101010101010101010101010101 $
b10000010000000000000101010101010101010101010101010101 '
#340000000000000
0#
#350000000000000
b10 4
b10000010000000000001101111010101101101111101110111111001010111111101011101010111110101010101010101001010101010101010101010101010101010101010101010101 !
b10000010000000000001101111010101101101111101110111111001010111111101011101010111110101010101010101001010101010101010101010101010101010101010101010101 *
b10000010000000000001101111010101101101111101110111111001010111111101011101010111110101010101010101001010101010101010101010101010101010101010101010101 3
b1000000000 0
b1000000000 :
b0 1
b0 ;
b10101010101010101010101010101010 "
b10101010101010101010101010101010 (
b10101010101010101010101010101010 2
b11 /
b10000000000000010000 +
b10000000000000010000 9
1#
#360000000000000
0#
#370000000000000
b1000000001 -
b1000000001 6
b11011110101011011011111011101111110010101111111010111010101111101010101010101010010101010101010100010010001101000101011001111000 .
b11011110101011011011111011101111110010101111111010111010101111101010101010101010010101010101010100010010001101000101011001111000 7
b1 4
b10101010101010101010101010101010 "
b10101010101010101010101010101010 (
b10101010101010101010101010101010 2
b10 /
1#
#380000000000000
0#
#390000000000000
b0 4
b10000010000000000001101111010101101101111101110111111001010111111101011101010111110101010101010101001010101010101010001001000110100010101100111100001 !
b10000010000000000001101111010101101101111101110111111001010111111101011101010111110101010101010101001010101010101010001001000110100010101100111100001 *
b10000010000000000001101111010101101101111101110111111001010111111101011101010111110101010101010101001010101010101010001001000110100010101100111100001 3
b11011110101011011011111011101111110010101111111010111010101111101010101010101010010101010101010101010101010101010101010101010101 .
b11011110101011011011111011101111110010101111111010111010101111101010101010101010010101010101010101010101010101010101010101010101 7
b1000000000 -
b1000000000 6
b100100011010001010110011110001 "
b100100011010001010110011110001 (
b100100011010001010110011110001 2
b1 /
b11011110101011011011111011101111110010101111111010111010101111101010101010101010010101010101010100010010001101000101011001111000 ,
b11011110101011011011111011101111110010101111111010111010101111101010101010101010010101010101010100010010001101000101011001111000 5
1#
#400000000000000
0#
#410000000000000
b0 /
b11011110101011011011111011101111110010101111111010111010101111101010101010101010010101010101010101010101010101010101010101010101 .
b11011110101011011011111011101111110010101111111010111010101111101010101010101010010101010101010101010101010101010101010101010101 7
b100100011010001010110011110000 "
b100100011010001010110011110000 (
b100100011010001010110011110000 2
b0 4
b10000010000000000000101010101010101010101010101010100 $
b10000010000000000000101010101010101010101010101010100 '
1#
